genedoku/Evolution.py
genedoku/__init__.py
genedoku/Chromosome.py
genedoku/Matrix.py
genedoku/SudokuChromosome.py
genedoku-1.0.0a4.dist-info/DESCRIPTION.rst
genedoku-1.0.0a4.dist-info/metadata.json
genedoku-1.0.0a4.dist-info/top_level.txt
genedoku-1.0.0a4.dist-info/WHEEL
genedoku-1.0.0a4.dist-info/RECORD
genedoku-1.0.0a4.dist-info/METADATA
