Metadata-Version: 2.0
Name: genedoku
Version: 1.0.0a4
Summary: A simple python package that solves sudokus using genetic algorithms
Home-page: https://github.com/AgustinCB/genedoku
Author: AgustinCB
Author-email: jnieve@gmail.com
License: GNU
Keywords: sudoku genetic algorithm solver
Platform: UNKNOWN
Classifier: Development Status :: 3 - Alpha
Classifier: Intended Audience :: Developers
Classifier: Topic :: Games/Entertainment :: Puzzle Games
Classifier: License :: OSI Approved :: GNU General Public License v2 or later (GPLv2+)
Classifier: Programming Language :: Python :: 2
Classifier: Programming Language :: Python :: 2.6
Classifier: Programming Language :: Python :: 2.7
